dmsp_to_aacgm/__init__.py
dmsp_to_aacgm/cli.py
dmsp_to_aacgm/lib/__init__.py
dmsp_to_aacgm/lib/dataset_model.py
dmsp_to_aacgm/lib/utils.py
dmsp_to_aacgm/lib/filetypes/__init__.py
dmsp_to_aacgm/lib/filetypes/factory.py
dmsp_to_aacgm/lib/filetypes/hdf5/__init__.py
dmsp_to_aacgm/lib/filetypes/hdf5/factory.py
dmsp_to_aacgm/lib/filetypes/hdf5/utils.py
dmsp_to_aacgm/lib/filetypes/hdf5/datasets/__init__.py
dmsp_to_aacgm/lib/filetypes/hdf5/datasets/flux.py
dmsp_to_aacgm/lib/filetypes/hdf5/datasets/mag.py
dmsp_to_aacgm-1.3.0.dist-info/LICENSE
dmsp_to_aacgm-1.3.0.dist-info/METADATA
dmsp_to_aacgm-1.3.0.dist-info/WHEEL
dmsp_to_aacgm-1.3.0.dist-info/entry_points.txt
dmsp_to_aacgm-1.3.0.dist-info/top_level.txt
dmsp_to_aacgm-1.3.0.dist-info/RECORD
