Metadata-Version: 2.2
Name: dmsp-to-aacgm
Version: 1.3.0
Summary: A CLI tool to convert geomagnetic coordinates in DMSP data files to AACGM coordinates.
Home-page: https://github.com/karzunn/dmsp-to-aacgm
Author: Carson O'Ffill
Author-email: offillcarson@gmail.com
License: MIT
Classifier: Programming Language :: Python :: 3.12
Classifier: Operating System :: OS Independent
Requires-Python: >=3.12
License-File: LICENSE
Requires-Dist: click>=8.1.3
Requires-Dist: aacgmv2>=2.7.0
Requires-Dist: h5py>=3.12.1
Dynamic: author
Dynamic: author-email
Dynamic: classifier
Dynamic: description
Dynamic: description-content-type
Dynamic: home-page
Dynamic: license
Dynamic: requires-dist
Dynamic: requires-python
Dynamic: summary
